[{"i":0,"p":2,"x":-7093.9,"z":-4520.5,"y":18.4,"hy":4.5,"hx":5.5,"hz":16.1,"yaw":-1.782,"vol":740.8},{"i":1,"p":2,"x":-6699.9,"z":-4475.5,"y":47.6,"hy":6.1,"hx":7.3,"hz":9.1,"yaw":1.017,"vol":1040.1},{"i":1,"p":2,"x":-6701,"z":-4487,"y":47.6,"hy":6.1,"hx":1.8,"hz":2.1,"yaw":1.017,"vol":1040.1},{"i":1,"p":2,"x":-6689.2,"z":-4480.3,"y":47.6,"hy":6.1,"hx":3,"hz":2.3,"yaw":2.588,"vol":1040.1},{"i":2,"p":4,"x":-6960.7,"z":-4402.6,"y":35.5,"hy":5.4,"hx":19.8,"hz":6.8,"yaw":-0.196,"vol":1407.3},{"i":8,"p":4,"x":-6641.2,"z":-4419.2,"y":46,"hy":4.1,"hx":7.3,"hz":1.9,"yaw":-1.613,"vol":672.1},{"i":8,"p":4,"x":-6647.8,"z":-4421.1,"y":46,"hy":4.1,"hx":8.8,"hz":4.8,"yaw":-1.613,"vol":672.1},{"i":9,"p":5,"x":-7139,"z":-4424.5,"y":28.7,"hy":4.3,"hx":14,"hz":6.5,"yaw":-0.061,"vol":719.2},{"i":10,"p":2,"x":-6473.9,"z":-4270.4,"y":121.5,"hy":4.4,"hx":7.7,"hz":1.9,"yaw":2.538,"vol":483.6},{"i":10,"p":2,"x":-6472.1,"z":-4272.6,"y":121.5,"hy":4.4,"hx":7.2,"hz":1,"yaw":2.538,"vol":483.6},{"i":10,"p":2,"x":-6470.9,"z":-4274.1,"y":121.5,"hy":4.4,"hx":5.6,"hz":1,"yaw":2.538,"vol":483.6},{"i":10,"p":2,"x":-6475.8,"z":-4267.2,"y":121.5,"hy":4.4,"hx":7.7,"hz":1.9,"yaw":2.538,"vol":483.6},{"i":10,"p":2,"x":-6477.4,"z":-4264.8,"y":121.5,"hy":4.4,"hx":7,"hz":1,"yaw":2.538,"vol":483.6},{"i":10,"p":2,"x":-6478.5,"z":-4263.2,"y":121.5,"hy":4.4,"hx":5,"hz":1,"yaw":-0.604,"vol":483.6}]